pyecoforest/__init__.py
pyecoforest/api.py
pyecoforest/const.py
pyecoforest/exceptions.py
pyecoforest/models/device.py
pyecoforest/py.typed
pyecoforest/ssl.py
pyecoforest-0.3.0.dist-info/LICENSE
pyecoforest-0.3.0.dist-info/METADATA
pyecoforest-0.3.0.dist-info/WHEEL
pyecoforest-0.3.0.dist-info/RECORD
